{
"meta":{"test_sets":[],"test_metrics":[],"learn_metrics":[{"best_value":"Min","name":"RMSE"}],"launch_mode":"Train","parameters":"","iteration_count":100,"learn_sets":["learn"],"name":"experiment"},
"iterations":[
{"learn":[14.005006],"iteration":0,"passed_time":0.004514847507,"remaining_time":0.4469699032},
{"learn":[13.14441192],"iteration":1,"passed_time":0.006378728801,"remaining_time":0.3125577113},
{"learn":[12.34258257],"iteration":2,"passed_time":0.008223400631,"remaining_time":0.2658899537},
{"learn":[11.64527793],"iteration":3,"passed_time":0.009521548805,"remaining_time":0.2285171713},
{"learn":[11.02766183],"iteration":4,"passed_time":0.01129208382,"remaining_time":0.2145495927},
{"learn":[10.43485794],"iteration":5,"passed_time":0.0128379166,"remaining_time":0.2011273601},
{"learn":[9.890641275],"iteration":6,"passed_time":0.01816691554,"remaining_time":0.2413604493},
{"learn":[9.492161212],"iteration":7,"passed_time":0.02124960571,"remaining_time":0.2443704657},
{"learn":[9.105082953],"iteration":8,"passed_time":0.02341885469,"remaining_time":0.2367906418},
{"learn":[8.674157135],"iteration":9,"passed_time":0.0250352765,"remaining_time":0.2253174885},
{"learn":[8.341743544],"iteration":10,"passed_time":0.02693524481,"remaining_time":0.2179306171},
{"learn":[8.049372916],"iteration":11,"passed_time":0.03009353921,"remaining_time":0.2206859542},
{"learn":[7.757318612],"iteration":12,"passed_time":0.03211063548,"remaining_time":0.2148942529},
{"learn":[7.522206899],"iteration":13,"passed_time":0.03404545353,"remaining_time":0.2091363574},
{"learn":[7.297756655],"iteration":14,"passed_time":0.03784685574,"remaining_time":0.2144655159},
{"learn":[7.088359431],"iteration":15,"passed_time":0.04233079457,"remaining_time":0.2222366715},
{"learn":[6.882113791],"iteration":16,"passed_time":0.04373001026,"remaining_time":0.2135053442},
{"learn":[6.704728832],"iteration":17,"passed_time":0.04518667844,"remaining_time":0.205850424},
{"learn":[6.563881962],"iteration":18,"passed_time":0.04691302513,"remaining_time":0.1999976334},
{"learn":[6.418790279],"iteration":19,"passed_time":0.04829795312,"remaining_time":0.1931918125},
{"learn":[6.315756953],"iteration":20,"passed_time":0.04965375521,"remaining_time":0.1867926982},
{"learn":[6.210157751],"iteration":21,"passed_time":0.05120750565,"remaining_time":0.1815538837},
{"learn":[6.115058449],"iteration":22,"passed_time":0.05251877488,"remaining_time":0.1758237246},
{"learn":[6.014819884],"iteration":23,"passed_time":0.05367716181,"remaining_time":0.1699776791},
{"learn":[5.93117229],"iteration":24,"passed_time":0.05509191205,"remaining_time":0.1652757361},
{"learn":[5.844857622],"iteration":25,"passed_time":0.05626838418,"remaining_time":0.160148478},
{"learn":[5.771145213],"iteration":26,"passed_time":0.05745266824,"remaining_time":0.1553349919},
{"learn":[5.704018229],"iteration":27,"passed_time":0.05889733871,"remaining_time":0.1514502995},
{"learn":[5.665806474],"iteration":28,"passed_time":0.06012316976,"remaining_time":0.1471981053},
{"learn":[5.616500369],"iteration":29,"passed_time":0.06173146702,"remaining_time":0.1440400897},
{"learn":[5.558023666],"iteration":30,"passed_time":0.06314001128,"remaining_time":0.1405374445},
{"learn":[5.510080976],"iteration":31,"passed_time":0.06446610869,"remaining_time":0.136990481},
{"learn":[5.468747792],"iteration":32,"passed_time":0.0664740391,"remaining_time":0.134962443},
{"learn":[5.429275534],"iteration":33,"passed_time":0.06770657833,"remaining_time":0.1314304168},
{"learn":[5.402117324],"iteration":34,"passed_time":0.06900003442,"remaining_time":0.1281429211},
{"learn":[5.367635151],"iteration":35,"passed_time":0.07018336421,"remaining_time":0.1247704253},
{"learn":[5.345181232],"iteration":36,"passed_time":0.0713679372,"remaining_time":0.1215183796},
{"learn":[5.319151269],"iteration":37,"passed_time":0.0729583124,"remaining_time":0.1190372465},
{"learn":[5.296134146],"iteration":38,"passed_time":0.07419728183,"remaining_time":0.1160521588},
{"learn":[5.269629003],"iteration":39,"passed_time":0.07538903467,"remaining_time":0.113083552},
{"learn":[5.251147059],"iteration":40,"passed_time":0.07682534269,"remaining_time":0.1105535419},
{"learn":[5.248003302],"iteration":41,"passed_time":0.07746383362,"remaining_time":0.1069738655},
{"learn":[5.232376509],"iteration":42,"passed_time":0.07879365927,"remaining_time":0.1044474088},
{"learn":[5.213524255],"iteration":43,"passed_time":0.08054448627,"remaining_time":0.1025111643},
{"learn":[5.189691584],"iteration":44,"passed_time":0.08173393819,"remaining_time":0.09989703556},
{"learn":[5.166052198],"iteration":45,"passed_time":0.08313508886,"remaining_time":0.09759336519},
{"learn":[5.140406659],"iteration":46,"passed_time":0.0843514127,"remaining_time":0.09511967816},
{"learn":[5.118929684],"iteration":47,"passed_time":0.08555432656,"remaining_time":0.09268385377},
{"learn":[5.108792602],"iteration":48,"passed_time":0.08706220661,"remaining_time":0.09061576606},
{"learn":[5.098141225],"iteration":49,"passed_time":0.08824649614,"remaining_time":0.08824649614},
{"learn":[5.085926393],"iteration":50,"passed_time":0.08940658837,"remaining_time":0.08590044765},
{"learn":[5.067816804],"iteration":51,"passed_time":0.09094745928,"remaining_time":0.08395150087},
{"learn":[5.049834901],"iteration":52,"passed_time":0.0924763188,"remaining_time":0.08200730158},
{"learn":[5.03838627],"iteration":53,"passed_time":0.09442459332,"remaining_time":0.08043576468},
{"learn":[5.033534248],"iteration":54,"passed_time":0.09525705964,"remaining_time":0.07793759425},
{"learn":[5.023726885],"iteration":55,"passed_time":0.09649989356,"remaining_time":0.07582134494},
{"learn":[5.01290392],"iteration":56,"passed_time":0.09769346609,"remaining_time":0.07369857968},
{"learn":[5.005569127],"iteration":57,"passed_time":0.09889244891,"remaining_time":0.07161177335},
{"learn":[4.989969032],"iteration":58,"passed_time":0.1002278776,"remaining_time":0.06964988106},
{"learn":[4.976762446],"iteration":59,"passed_time":0.1014223315,"remaining_time":0.06761488768},
{"learn":[4.967222715],"iteration":60,"passed_time":0.102595851,"remaining_time":0.0655940687},
{"learn":[4.954407599],"iteration":61,"passed_time":0.1038286674,"remaining_time":0.06363692515},
{"learn":[4.942125056],"iteration":62,"passed_time":0.1054005695,"remaining_time":0.06190192179},
{"learn":[4.930230716],"iteration":63,"passed_time":0.1069303792,"remaining_time":0.06014833832},
{"learn":[4.921695642],"iteration":64,"passed_time":0.1084443149,"remaining_time":0.05839309263},
{"learn":[4.906405625],"iteration":65,"passed_time":0.1099034467,"remaining_time":0.05661692707},
{"learn":[4.894330248],"iteration":66,"passed_time":0.1111259323,"remaining_time":0.05473366814},
{"learn":[4.88211557],"iteration":67,"passed_time":0.1123455323,"remaining_time":0.05286848578},
{"learn":[4.877946398],"iteration":68,"passed_time":0.1135322663,"remaining_time":0.05100725008},
{"learn":[4.863182126],"iteration":69,"passed_time":0.1149367323,"remaining_time":0.04925859957},
{"learn":[4.84646533],"iteration":70,"passed_time":0.1161419972,"remaining_time":0.04743828056},
{"learn":[4.838014752],"iteration":71,"passed_time":0.1173457893,"remaining_time":0.0456344736},
{"learn":[4.82981137],"iteration":72,"passed_time":0.1185195193,"remaining_time":0.0438359866},
{"learn":[4.817094767],"iteration":73,"passed_time":0.1200282666,"remaining_time":0.04217209368},
{"learn":[4.808314151],"iteration":74,"passed_time":0.1219161032,"remaining_time":0.04063870108},
{"learn":[4.796235023],"iteration":75,"passed_time":0.1235954188,"remaining_time":0.03903013226},
{"learn":[4.784434534],"iteration":76,"passed_time":0.1251193156,"remaining_time":0.03737330205},
{"learn":[4.774402487],"iteration":77,"passed_time":0.1267215035,"remaining_time":0.03574196251},
{"learn":[4.76731896],"iteration":78,"passed_time":0.1282553331,"remaining_time":0.0340931898},
{"learn":[4.75934113],"iteration":79,"passed_time":0.1295067773,"remaining_time":0.03237669433},
{"learn":[4.754106378],"iteration":80,"passed_time":0.1307016332,"remaining_time":0.03065840778},
{"learn":[4.744002932],"iteration":81,"passed_time":0.1319237082,"remaining_time":0.02895886277},
{"learn":[4.731700554],"iteration":82,"passed_time":0.1330580026,"remaining_time":0.02725284391},
{"learn":[4.723284153],"iteration":83,"passed_time":0.1345359797,"remaining_time":0.0256259009},
{"learn":[4.712232782],"iteration":84,"passed_time":0.1361235596,"remaining_time":0.02402180463},
{"learn":[4.703046867],"iteration":85,"passed_time":0.1376630765,"remaining_time":0.02241026827},
{"learn":[4.698601855],"iteration":86,"passed_time":0.1389188661,"remaining_time":0.02075799149},
{"learn":[4.692429407],"iteration":87,"passed_time":0.1400880987,"remaining_time":0.01910292255},
{"learn":[4.675027364],"iteration":88,"passed_time":0.1412466597,"remaining_time":0.01745745232},
{"learn":[4.662368584],"iteration":89,"passed_time":0.1426974363,"remaining_time":0.0158552707},
{"learn":[4.646206172],"iteration":90,"passed_time":0.1439365748,"remaining_time":0.01423548542},
{"learn":[4.641245848],"iteration":91,"passed_time":0.1451076718,"remaining_time":0.01261805841},
{"learn":[4.633900435],"iteration":92,"passed_time":0.146298201,"remaining_time":0.01101169255},
{"learn":[4.624738236],"iteration":93,"passed_time":0.1474794992,"remaining_time":0.009413585054},
{"learn":[4.612798287],"iteration":94,"passed_time":0.1492988098,"remaining_time":0.007857832095},
{"learn":[4.605222001],"iteration":95,"passed_time":0.1508043543,"remaining_time":0.006283514762},
{"learn":[4.601725912],"iteration":96,"passed_time":0.1526993129,"remaining_time":0.004722659161},
{"learn":[4.59722371],"iteration":97,"passed_time":0.1539052855,"remaining_time":0.003140924194},
{"learn":[4.580235665],"iteration":98,"passed_time":0.1550900686,"remaining_time":0.00156656635},
{"learn":[4.57591791],"iteration":99,"passed_time":0.1564292388,"remaining_time":0}
]}